snap/__init__.py
snap/chain.py
snap/config.py
snap/node.py
snap/parallel.py
snap/status.py
snap/test_queue.py
snap/timing.py
snap/elements/__init__.py
snap/elements/misc.py
snap/elements/output.py
snap/elements/source.py
snap/elements/timing.py
snap/elements/tqdm.py
snap/elements/io/__init__.py
snap/elements/io/hop.py
snap/elements/io/queue.py
snap/elements/io/zmq.py
snap_base-2.0.3.dist-info/LICENSE
snap_base-2.0.3.dist-info/METADATA
snap_base-2.0.3.dist-info/WHEEL
snap_base-2.0.3.dist-info/entry_points.txt
snap_base-2.0.3.dist-info/top_level.txt
snap_base-2.0.3.dist-info/RECORD
