Metadata-Version: 2.1
Name: snap-base
Version: 2.0.3
Summary: SuperNova Async Pipeline: base package
Author-email: Andrey Sheshukov <ash@jinr.ru>
Project-URL: Repository, https://github.com/Sheshuk/snap-base
Classifier: License :: OSI Approved :: GNU General Public License v3 (GPLv3)
Requires-Python: >=3.9
License-File: LICENSE
Requires-Dist: pyyaml >=3.5
Requires-Dist: tqdm >=4.53
Requires-Dist: pyzmq >=20
Requires-Dist: numpy
Provides-Extra: doc
Requires-Dist: sphinx ; extra == 'doc'
Requires-Dist: sphinx-rtd-theme ; extra == 'doc'
Requires-Dist: sphinx-argparse ; extra == 'doc'
Provides-Extra: io
Requires-Dist: hop-client ==0.5 ; extra == 'io'
